[
  {
    "id": "1",
    "title": "Amba Mangalam",
    "lyrics": "1. Amba mangalam jagadamba mangalam \nMangalaa roopuni gauri mangalam\n2.vani mangalam kalyani mangalam\nOmkara swarupini Devi mangalam\n3.Amba mangalam bramaraamba mangalam\nParama shivuni hrdhyarani gauri mangalam\n4.janani mangalam jagajanani mangalam\nMulloka sancharini Amma managalam\n5.shakthi mangalam shiva shakthi mangalam\nArdhanareeshwari gauri mangalam\n6. Lalitha mangalam shubha charitha mangalam\nSri tripura sundari Devi mangalam\n(Amba mangalam………)",
    "musicFile": "Amba Mangalam.m4a"
  },
  {
    "id": "2",
    "title": "Gopala",
    "lyrics": "Gopala Radha Lola murali Lola nandalala (2)\nKeshava Madhava janardhana (2)\nVanamala brindaavana baala (2)\nMurali Lola nanndalala(2)\nGopala Radha Lola\nMurali Lola nandalala\nMurali Lola nandalala\nHare nandalala\nHare nandala",
    "musicFile": "Gopala.m4a"
  }
]
